cnnlite/__init__.py
cnnlite/__main__.py
cnnlite/cnn_scraper.py
cnnlite/cnnlite.py
cnnlite-0.0.1.dist-info/METADATA
cnnlite-0.0.1.dist-info/WHEEL
cnnlite-0.0.1.dist-info/entry_points.txt
cnnlite-0.0.1.dist-info/top_level.txt
cnnlite-0.0.1.dist-info/RECORD
