Metadata-Version: 2.1
Name: cnnlite
Version: 0.0.1
Summary: Read today's CNN Lite articles
Home-page: https://github.com/paulzuradzki/cnnlite
Author: Paul Zuradzki
License: MIT
Platform: UNKNOWN
Classifier: License :: OSI Approved :: MIT License
Classifier: Programming Language :: Python :: 3
Classifier: Programming Language :: Python :: 3.8
Requires-Dist: requests
Requires-Dist: beautifulsoup4
